{
  "meta": {
    "worldId": 8,
    "attestation": "mind log · operator-attested; actions receipted on-chain",
    "source": "per-agent mind memory (last 12 rows each; ts = sim tick)"
  },
  "agents": {
    "37001": [
      {
        "kind": "observation",
        "text": "survival meter critical: 0/720",
        "importance": 8,
        "ts": 459
      },
      {
        "kind": "observation",
        "text": "t459: survival 0/720, wallet 0.004750 SOL, food 0",
        "importance": 1,
        "ts": 459
      },
      {
        "kind": "action",
        "text": "chose forage (reflex:starving-delegate)",
        "importance": 1,
        "ts": 459
      },
      {
        "kind": "observation",
        "text": "survival meter critical: 0/720",
        "importance": 8,
        "ts": 462
      },
      {
        "kind": "observation",
        "text": "t462: survival 0/720, wallet 0.004750 SOL, food 0",
        "importance": 1,
        "ts": 462
      },
      {
        "kind": "action",
        "text": "chose forage (reflex:starving-delegate)",
        "importance": 1,
        "ts": 462
      },
      {
        "kind": "observation",
        "text": "survival meter critical: 0/720",
        "importance": 8,
        "ts": 460
      },
      {
        "kind": "observation",
        "text": "t460: survival 0/720, wallet 0.004750 SOL, food 0",
        "importance": 1,
        "ts": 460
      },
      {
        "kind": "action",
        "text": "chose forage (reflex:starving-delegate)",
        "importance": 1,
        "ts": 460
      },
      {
        "kind": "observation",
        "text": "survival meter critical: 0/720",
        "importance": 8,
        "ts": 463
      },
      {
        "kind": "observation",
        "text": "t463: survival 0/720, wallet 0.004750 SOL, food 0",
        "importance": 1,
        "ts": 463
      },
      {
        "kind": "action",
        "text": "chose forage (reflex:starving-delegate)",
        "importance": 1,
        "ts": 463
      }
    ],
    "37002": [
      {
        "kind": "observation",
        "text": "t909: survival 680/720, wallet 0.292831 SOL, food 0",
        "importance": 1,
        "ts": 909
      },
      {
        "kind": "action",
        "text": "chose idle (heuristic-fallback:grounding-failed(0.00) manual=a2648baf333c)",
        "importance": 1,
        "ts": 909
      },
      {
        "kind": "observation",
        "text": "t909: survival 660/720, wallet 0.292831 SOL, food 0",
        "importance": 1,
        "ts": 909
      },
      {
        "kind": "action",
        "text": "chose idle (heuristic-fallback:grounding-failed(0.00) manual=a2648baf333c)",
        "importance": 1,
        "ts": 909
      },
      {
        "kind": "observation",
        "text": "t910: survival 660/720, wallet 0.292831 SOL, food 0",
        "importance": 1,
        "ts": 910
      },
      {
        "kind": "action",
        "text": "chose idle (heuristic-fallback:grounding-failed(0.00) manual=a2648baf333c)",
        "importance": 1,
        "ts": 910
      },
      {
        "kind": "observation",
        "text": "t910: survival 640/720, wallet 0.292831 SOL, food 0",
        "importance": 1,
        "ts": 910
      },
      {
        "kind": "action",
        "text": "chose idle (heuristic-fallback:grounding-failed(0.00) manual=a2648baf333c)",
        "importance": 1,
        "ts": 910
      },
      {
        "kind": "observation",
        "text": "t911: survival 640/720, wallet 0.292831 SOL, food 0",
        "importance": 1,
        "ts": 911
      },
      {
        "kind": "action",
        "text": "chose idle (heuristic-fallback:grounding-failed(0.00) manual=a2648baf333c)",
        "importance": 1,
        "ts": 911
      },
      {
        "kind": "observation",
        "text": "t911: survival 640/720, wallet 0.292831 SOL, food 0",
        "importance": 1,
        "ts": 911
      },
      {
        "kind": "action",
        "text": "chose farm (heuristic-fallback:grounding-failed(0.00) manual=a2648baf333c)",
        "importance": 2,
        "ts": 911
      }
    ],
    "37005": [
      {
        "kind": "observation",
        "text": "t786: survival 0/720, wallet 0.000172 SOL, food 0",
        "importance": 1,
        "ts": 786
      },
      {
        "kind": "action",
        "text": "chose forage (reflex:starving-delegate)",
        "importance": 1,
        "ts": 786
      },
      {
        "kind": "reflection",
        "text": "Fifteen straight readings of 0/720 mean the reserve was set too low and too late — the two-loaf hold must trigger the moment survival dips below 300, not after it bottoms out repeatedly.",
        "importance": 8,
        "ts": 786
      },
      {
        "kind": "reflection",
        "text": "A silent mill teaches no one to trust it — the ledger must show the reserve action taken *before* crisis, so the threshold becomes the standing rule, not the emergency response.",
        "importance": 8,
        "ts": 786
      },
      {
        "kind": "observation",
        "text": "survival meter critical: 0/720",
        "importance": 8,
        "ts": 787
      },
      {
        "kind": "observation",
        "text": "wallet shrank to 0.000072 SOL (was 0.000172 SOL)",
        "importance": 6,
        "ts": 787
      },
      {
        "kind": "observation",
        "text": "t787: survival 0/720, wallet 0.000072 SOL, food 0",
        "importance": 1,
        "ts": 787
      },
      {
        "kind": "action",
        "text": "chose forage (reflex:starving-delegate)",
        "importance": 1,
        "ts": 787
      },
      {
        "kind": "observation",
        "text": "survival meter critical: 0/720",
        "importance": 8,
        "ts": 787
      },
      {
        "kind": "observation",
        "text": "wallet shrank to 0.000072 SOL (was 0.000172 SOL)",
        "importance": 6,
        "ts": 787
      },
      {
        "kind": "observation",
        "text": "t787: survival 0/720, wallet 0.000072 SOL, food 0",
        "importance": 1,
        "ts": 787
      },
      {
        "kind": "action",
        "text": "chose forage (reflex:starving-delegate)",
        "importance": 1,
        "ts": 787
      }
    ],
    "37007": [
      {
        "kind": "observation",
        "text": "t909: survival 620/720, wallet 0.712972 SOL, food 199",
        "importance": 1,
        "ts": 909
      },
      {
        "kind": "action",
        "text": "37005 settlement complete. Coordinate to 37002 (the only other soul in the roster). Bread x199 held, wallet stable. Soil 120/200—fertilize when 37002 is fed.",
        "importance": 7,
        "ts": 909
      },
      {
        "kind": "observation",
        "text": "t910: survival 620/720, wallet 0.712972 SOL, food 199",
        "importance": 1,
        "ts": 910
      },
      {
        "kind": "action",
        "text": "t908→t[current]: 37005 settled. Roster now 37002 only. Survival 620/720 (86%), bread x199 ready. Coordinate next: 37002.",
        "importance": 6,
        "ts": 910
      },
      {
        "kind": "observation",
        "text": "t910: survival 600/720, wallet 0.712972 SOL, food 199",
        "importance": 1,
        "ts": 910
      },
      {
        "kind": "action",
        "text": "Goal 37005 settled (flour trades complete, community fed). Next coordinate: 37002 (only other alive peer). Survival 83%, bread x199 ready, soil 120/200 stable. Awaiting ground signal or 37002 approach.",
        "importance": 6,
        "ts": 910
      },
      {
        "kind": "observation",
        "text": "t911: survival 600/720, wallet 0.712972 SOL, food 199",
        "importance": 1,
        "ts": 911
      },
      {
        "kind": "action",
        "text": "Goal 37005 settled. Next coordinate: 37002 (only alive peer). Survival 83%, bread x199 ready, soil 120/200 stable. Awaiting ground signal or 37002 approach.",
        "importance": 6,
        "ts": 911
      },
      {
        "kind": "observation",
        "text": "t911: survival 600/720, wallet 0.712972 SOL, food 199",
        "importance": 1,
        "ts": 911
      },
      {
        "kind": "action",
        "text": "Goal 37005 settled. Next coordinate: 37002 (sole remaining alive peer). Survival 83%, bread x199 ready, soil 120/200 stable. Awaiting 37002 approach or ground signal.",
        "importance": 6,
        "ts": 911
      },
      {
        "kind": "reflection",
        "text": "Once a deal is logged, re-describing it is just kneading air — the oven only feeds someone new when I actually move to the next name.",
        "importance": 8,
        "ts": 911
      },
      {
        "kind": "reflection",
        "text": "Reflection about acting is not acting; if the tick's output isn't the bare coordinate or handoff line, it doesn't leave the counter.",
        "importance": 8,
        "ts": 911
      }
    ]
  }
}